{
  "frontmatter": {
    "type": "method",
    "interface": "ICircularPatternFeatureData",
    "member": "ISetSkippedItemArray",
    "returns": "void",
    "parameters": [
      {
        "name": "FeatCount",
        "type": "System.Int32",
        "description": "Number of instances to skip"
      },
      {
        "name": "ArrayDataIn",
        "type": "System.Int32",
        "description": "in-process, unmanaged C++: Pointer to an array that represents the skipped items of size FeatCount VBA, VB.NET, C#, and C++/CLI: Not supported See In-process Methods for details about this type of method."
      }
    ],
    "docset": "sldworksapi",
    "deprecated": false,
    "since_version": "unknown",
    "categories": [
      "features"
    ],
    "related": [
      "ICircularPatternFeatureData.GetSkippedItemCount",
      "ICircularPatternFeatureData.IGetSkippedItemArray",
      "ICircularPatternFeatureData.SkippedItemArray"
    ],
    "keywords": [
      "isetskippeditemarray",
      "icircularpatternfeaturedata",
      "circular",
      "pattern",
      "feature",
      "data",
      "skipped",
      "item",
      "array",
      "feat",
      "count",
      "int32",
      "void"
    ]
  },
  "title": "ICircularPatternFeatureData.ISetSkippedItemArray",
  "description": "Sets the list of skipped items in this circular pattern.",
  "signature": "void ISetSkippedItemArray( \n   System.Int32\nFeatCount\n,\n   ref System.Int32\nArrayDataIn\n)",
  "parameters": [
    {
      "name": "FeatCount",
      "type": "System.Int32",
      "description": "Number of instances to skip"
    },
    {
      "name": "ArrayDataIn",
      "type": "System.Int32",
      "description": "in-process, unmanaged C++: Pointer to an array that represents the skipped items of size FeatCount VBA, VB.NET, C#, and C++/CLI: Not supported See In-process Methods for details about this type of method."
    }
  ],
  "returns": "",
  "remarks": "See\nAccessing Selections that Define Features\nfor additional details on using this method.",
  "examples": [],
  "related": [
    "ICircularPatternFeatureData.GetSkippedItemCount",
    "ICircularPatternFeatureData.IGetSkippedItemArray",
    "ICircularPatternFeatureData.SkippedItemArray"
  ]
}