{
  "frontmatter": {
    "type": "property",
    "interface": "ISwOLEObject",
    "member": "BufferSize",
    "returns": "System.Int32",
    "parameters": [],
    "docset": "sldworksapi",
    "deprecated": false,
    "since_version": "unknown",
    "categories": [
      "documents"
    ],
    "related": [
      "ISwOLEObject.Buffer"
    ],
    "keywords": [
      "buffersize",
      "iswoleobject",
      "sw",
      "ole",
      "object",
      "buffer",
      "size",
      "int32"
    ],
    "readonly": true
  },
  "title": "ISwOLEObject.BufferSize",
  "description": "Gets the size of the OLE object data.",
  "signature": "System.Int32 BufferSize {get;}",
  "parameters": [],
  "returns": "Size of the OLE object data",
  "remarks": "Call this method before calling\nISwOLEObject::IGetBuffer\nto get the size of the array for that method.",
  "examples": [
    {
      "title": "ISwOLEObject",
      "href": "ms-xhelp:///?id=SolidWorks.Interop.sldworks~SolidWorks.Interop.sldworks.ISwOLEObject",
      "code_blocks": []
    }
  ],
  "related": [
    "ISwOLEObject.Buffer"
  ]
}