{
  "frontmatter": {
    "type": "method",
    "interface": "IModelDoc",
    "member": "CreatePlanePerCurveAndPassPoint",
    "returns": "void",
    "parameters": [
      {
        "name": "OrigAtCurve",
        "type": "System.Boolean",
        "description": ""
      }
    ],
    "docset": "sldworksapi",
    "deprecated": true,
    "since_version": "unknown",
    "categories": [
      "documents"
    ],
    "related": [],
    "keywords": [
      "createplanepercurveandpasspoint",
      "imodeldoc",
      "model",
      "doc",
      "create",
      "plane",
      "per",
      "curve",
      "pass",
      "point",
      "orig",
      "boolean",
      "void"
    ]
  },
  "title": "IModelDoc.CreatePlanePerCurveAndPassPoint",
  "description": "Obsolete. Superseded by IModelDoc2::CreatePlanePerCurveAndPassPoint.",
  "signature": "void CreatePlanePerCurveAndPassPoint( \n   System.Boolean\nOrigAtCurve\n)",
  "parameters": [
    {
      "name": "OrigAtCurve",
      "type": "System.Boolean",
      "description": ""
    }
  ],
  "returns": "",
  "remarks": "",
  "examples": [],
  "related": []
}