{
  "frontmatter": {
    "type": "method",
    "interface": "IModelDoc",
    "member": "IInsertDatumTag2",
    "returns": "DatumTag",
    "parameters": [],
    "docset": "sldworksapi",
    "deprecated": true,
    "since_version": "unknown",
    "categories": [
      "documents"
    ],
    "related": [],
    "keywords": [
      "iinsertdatumtag2",
      "imodeldoc",
      "model",
      "doc",
      "insert",
      "datum",
      "tag2",
      "tag"
    ]
  },
  "title": "IModelDoc.IInsertDatumTag2",
  "description": "Obsolete. Superseded by IModelDoc2::IInsertDatumTag2.",
  "signature": "DatumTag IInsertDatumTag2()",
  "parameters": [],
  "returns": "",
  "remarks": "",
  "examples": [],
  "related": []
}