{
  "frontmatter": {
    "type": "property",
    "interface": "ISplitLineFeatureData",
    "member": "SplitAll",
    "returns": "System.Boolean",
    "parameters": [],
    "docset": "sldworksapi",
    "deprecated": false,
    "since_version": "unknown",
    "categories": [
      "features"
    ],
    "related": [
      "ISplitLineFeatureData.GetSplitTargetsCount",
      "ISplitLineFeatureData.IGetSplitTargets",
      "ISplitLineFeatureData.ISetSplitTargets",
      "ISplitLineFeatureData.SplitTargets"
    ],
    "keywords": [
      "splitall",
      "isplitlinefeaturedata",
      "split",
      "line",
      "feature",
      "data",
      "all",
      "boolean"
    ],
    "readonly": null
  },
  "title": "ISplitLineFeatureData.SplitAll",
  "description": "Gets or sets whether to split all targets.",
  "signature": "System.Boolean SplitAll {get; set;}",
  "parameters": [],
  "returns": "True to split all targets, false to not",
  "remarks": "",
  "examples": [],
  "related": [
    "ISplitLineFeatureData.GetSplitTargetsCount",
    "ISplitLineFeatureData.IGetSplitTargets",
    "ISplitLineFeatureData.ISetSplitTargets",
    "ISplitLineFeatureData.SplitTargets"
  ]
}