{
  "frontmatter": {
    "type": "method",
    "interface": "IView",
    "member": "GetDisplayData",
    "returns": "System.Object",
    "parameters": [],
    "docset": "sldworksapi",
    "deprecated": true,
    "since_version": "unknown",
    "categories": [
      "drawings",
      "ui"
    ],
    "related": [],
    "keywords": [
      "getdisplaydata",
      "iview",
      "view",
      "display",
      "data",
      "object"
    ]
  },
  "title": "IView.GetDisplayData",
  "description": "Obsolete. Superseded by IView::GetDisplayData3 and IView::IGetDisplayData3.",
  "signature": "System.Object GetDisplayData()",
  "parameters": [],
  "returns": "",
  "remarks": "",
  "examples": [],
  "related": []
}