{
  "frontmatter": {
    "type": "property",
    "interface": "IView",
    "member": "LinkParentConfiguration",
    "returns": "System.Boolean",
    "parameters": [],
    "docset": "sldworksapi",
    "deprecated": false,
    "since_version": "unknown",
    "categories": [
      "drawings",
      "ui"
    ],
    "related": [],
    "keywords": [
      "linkparentconfiguration",
      "iview",
      "view",
      "link",
      "parent",
      "configuration",
      "boolean",
      "projected",
      "vb",
      "net",
      "vba"
    ],
    "readonly": null
  },
  "title": "IView.LinkParentConfiguration",
  "description": "Gets or sets whether to link a projected or auxiliary view with the parent configuration.",
  "signature": "System.Boolean LinkParentConfiguration {get; set;}",
  "parameters": [],
  "returns": "True to link a projected or auxiliary view with the parent configuration, false to not",
  "remarks": "After setting this property, call\nIModelDoc2::EditRebuild3\n.",
  "examples": [
    {
      "title": "Link Projected View to Parent Configuration (C#)",
      "href": "Link_Projected_View_to_Parent_Configuration_Example_CSharp.htm",
      "code_blocks": []
    },
    {
      "title": "Link Projected View to Parent Configuration (VB.NET)",
      "href": "Link_Projected_View_to_Parent_Configuration_Example_VBNET.htm",
      "code_blocks": []
    },
    {
      "title": "Link Projected View to Parent Configuration (VBA)",
      "href": "Link_Projected_View_to_Parent_Configuration_Example_VB.htm",
      "code_blocks": []
    }
  ],
  "related": []
}