{
  "frontmatter": {
    "type": "method",
    "interface": "IFeatureManager",
    "member": "HoleWizard4",
    "returns": "Feature",
    "parameters": [
      {
        "name": "GenericHoleType",
        "type": "System.Int32",
        "description": "Hole type as defined in swWzdGeneralHoleTypes_e"
      },
      {
        "name": "StandardIndex",
        "type": "System.Int32",
        "description": "Standard property as defined in swWzdHoleStandards_e"
      },
      {
        "name": "FastenerTypeIndex",
        "type": "System.Int32",
        "description": "Screw type as defined in swWzdHoleStandardFastenerTypes_e"
      },
      {
        "name": "SSize",
        "type": "System.String",
        "description": "Size of the hole"
      },
      {
        "name": "EndType",
        "type": "System.Int16",
        "description": "End type as defined in swEndConditions_e"
      },
      {
        "name": "Diameter",
        "type": "System.Double",
        "description": "Diameter of the hole in meters"
      },
      {
        "name": "Depth",
        "type": "System.Double",
        "description": "Depth of the hole in meters"
      },
      {
        "name": "Value1",
        "type": "System.Double",
        "description": "Hole-related parameter"
      },
      {
        "name": "Value2",
        "type": "System.Double",
        "description": "Hole-related parameter"
      },
      {
        "name": "Value3",
        "type": "System.Double",
        "description": "Hole-related parameter"
      },
      {
        "name": "Value4",
        "type": "System.Double",
        "description": "Hole-related parameter"
      },
      {
        "name": "Value5",
        "type": "System.Double",
        "description": "Hole-related parameter"
      },
      {
        "name": "Value6",
        "type": "System.Double",
        "description": "Hole-related parameter"
      },
      {
        "name": "Value7",
        "type": "System.Double",
        "description": "Hole-related parameter"
      },
      {
        "name": "Value8",
        "type": "System.Double",
        "description": "Hole-related parameter"
      },
      {
        "name": "Value9",
        "type": "System.Double",
        "description": "Hole-related parameter"
      },
      {
        "name": "Value10",
        "type": "System.Double",
        "description": "Hole-related parameter"
      },
      {
        "name": "Value11",
        "type": "System.Double",
        "description": "Hole-related parameter"
      },
      {
        "name": "Value12",
        "type": "System.Double",
        "description": "Hole-related parameter"
      },
      {
        "name": "ThreadClass",
        "type": "System.String",
        "description": "One of the following thread classes: 1B 2B 3B Applies to ANSI inch standard only"
      },
      {
        "name": "RevDir",
        "type": "System.Boolean",
        "description": "True to reverse the direction of the hole, false to not (see Remarks )"
      },
      {
        "name": "UseFeatScope",
        "type": "System.Boolean",
        "description": "True if the feature only affects selected bodies, false if the feature affects all bodies"
      },
      {
        "name": "UseAutoSelect",
        "type": "System.Boolean",
        "description": "True to automatically select all bodies and have the feature affect those bodies, false to select the bodies the feature affects"
      },
      {
        "name": "AssemblyFeatureScope",
        "type": "System.Boolean",
        "description": "True if the assembly feature only affects selected bodies in the assembly, false if the assembly feature affects all bodies in the assembly"
      },
      {
        "name": "AutoSelectComponents",
        "type": "System.Boolean",
        "description": "True to auto-select all affected components, false to only use the selected components"
      },
      {
        "name": "PropagateFeatureToParts",
        "type": "System.Boolean",
        "description": "True to propagate the assembly feature to the components, false to not"
      }
    ],
    "docset": "sldworksapi",
    "deprecated": true,
    "since_version": "unknown",
    "categories": [
      "features"
    ],
    "related": [],
    "keywords": [
      "holewizard4",
      "ifeaturemanager",
      "feature",
      "manager",
      "hole",
      "wizard4",
      "generic",
      "type",
      "int32",
      "standard",
      "index",
      "fastener",
      "size",
      "string",
      "end",
      "int16",
      "diameter",
      "double",
      "depth",
      "value1",
      "value2",
      "value3",
      "value4",
      "value5",
      "value6",
      "value7",
      "value8",
      "value9",
      "value10",
      "value11",
      "value12",
      "thread",
      "rev",
      "dir",
      "boolean",
      "use",
      "feat",
      "scope",
      "auto",
      "select",
      "assembly",
      "components",
      "propagate",
      "parts"
    ]
  },
  "title": "IFeatureManager.HoleWizard4",
  "description": "Obsolete. Superseded by IFeatureManager::HoleWizard5.",
  "signature": "Feature HoleWizard4( \n   System.Int32\nGenericHoleType\n,\n   System.Int32\nStandardIndex\n,\n   System.Int32\nFastenerTypeIndex\n,\n   System.String\nSSize\n,\n   System.Int16\nEndType\n,\n   System.Double\nDiameter\n,\n   System.Double\nDepth\n,\n   System.Double\nValue1\n,\n   System.Double\nValue2\n,\n   System.Double\nValue3\n,\n   System.Double\nValue4\n,\n   System.Double\nValue5\n,\n   System.Double\nValue6\n,\n   System.Double\nValue7\n,\n   System.Double\nValue8\n,\n   System.Double\nValue9\n,\n   System.Double\nValue10\n,\n   System.Double\nValue11\n,\n   System.Double\nValue12\n,\n   System.String\nThreadClass\n,\n   System.Boolean\nRevDir\n,\n   System.Boolean\nUseFeatScope\n,\n   System.Boolean\nUseAutoSelect\n,\n   System.Boolean\nAssemblyFeatureScope\n,\n   System.Boolean\nAutoSelectComponents\n,\n   System.Boolean\nPropagateFeatureToParts\n)",
  "parameters": [
    {
      "name": "GenericHoleType",
      "type": "System.Int32",
      "description": "Hole type as defined in swWzdGeneralHoleTypes_e"
    },
    {
      "name": "StandardIndex",
      "type": "System.Int32",
      "description": "Standard property as defined in swWzdHoleStandards_e"
    },
    {
      "name": "FastenerTypeIndex",
      "type": "System.Int32",
      "description": "Screw type as defined in swWzdHoleStandardFastenerTypes_e"
    },
    {
      "name": "SSize",
      "type": "System.String",
      "description": "Size of the hole"
    },
    {
      "name": "EndType",
      "type": "System.Int16",
      "description": "End type as defined in swEndConditions_e"
    },
    {
      "name": "Diameter",
      "type": "System.Double",
      "description": "Diameter of the hole in meters"
    },
    {
      "name": "Depth",
      "type": "System.Double",
      "description": "Depth of the hole in meters"
    },
    {
      "name": "Value1",
      "type": "System.Double",
      "description": "Hole-related parameter"
    },
    {
      "name": "Value2",
      "type": "System.Double",
      "description": "Hole-related parameter"
    },
    {
      "name": "Value3",
      "type": "System.Double",
      "description": "Hole-related parameter"
    },
    {
      "name": "Value4",
      "type": "System.Double",
      "description": "Hole-related parameter"
    },
    {
      "name": "Value5",
      "type": "System.Double",
      "description": "Hole-related parameter"
    },
    {
      "name": "Value6",
      "type": "System.Double",
      "description": "Hole-related parameter"
    },
    {
      "name": "Value7",
      "type": "System.Double",
      "description": "Hole-related parameter"
    },
    {
      "name": "Value8",
      "type": "System.Double",
      "description": "Hole-related parameter"
    },
    {
      "name": "Value9",
      "type": "System.Double",
      "description": "Hole-related parameter"
    },
    {
      "name": "Value10",
      "type": "System.Double",
      "description": "Hole-related parameter"
    },
    {
      "name": "Value11",
      "type": "System.Double",
      "description": "Hole-related parameter"
    },
    {
      "name": "Value12",
      "type": "System.Double",
      "description": "Hole-related parameter"
    },
    {
      "name": "ThreadClass",
      "type": "System.String",
      "description": "One of the following thread classes: 1B 2B 3B Applies to ANSI inch standard only"
    },
    {
      "name": "RevDir",
      "type": "System.Boolean",
      "description": "True to reverse the direction of the hole, false to not (see Remarks )"
    },
    {
      "name": "UseFeatScope",
      "type": "System.Boolean",
      "description": "True if the feature only affects selected bodies, false if the feature affects all bodies"
    },
    {
      "name": "UseAutoSelect",
      "type": "System.Boolean",
      "description": "True to automatically select all bodies and have the feature affect those bodies, false to select the bodies the feature affects"
    },
    {
      "name": "AssemblyFeatureScope",
      "type": "System.Boolean",
      "description": "True if the assembly feature only affects selected bodies in the assembly, false if the assembly feature affects all bodies in the assembly"
    },
    {
      "name": "AutoSelectComponents",
      "type": "System.Boolean",
      "description": "True to auto-select all affected components, false to only use the selected components"
    },
    {
      "name": "PropagateFeatureToParts",
      "type": "System.Boolean",
      "description": "True to propagate the assembly feature to the components, false to not"
    }
  ],
  "returns": "Feature",
  "remarks": "To add a hole at multiple locations, preselect the sketch points and do not specify any selection marks.\nBefore creating a hole using a reference plane and IFeatureManager::HoleWizard4, determine the value of the RevDir parameter as follows:\nIf the material is on one side of the reference plane, then RevDir is false.\nIf the material is on both sides of the reference plane, then compare the distances between the reference plane and the material on both sides. If the distance between the reference plane and the material along its normal direction is bigger, then RevDir is true; otherwise, RevDir is false.\nYou can also use\nIModelDoc2::RayIntersections\nand\nIModelDoc2::GetRayIntersectionsPoints\nto find out if the material is on one side or both sides and to compare the distances.\nThe screw fit is defined as\nswWzdHoleScrewClearanceTypes_e\nand only used if a hole diameter is not specified; default value is NORMAL_FIT. The drill angle defaults to 118\n,\nif not specified. Input angles are in radians; input values are in meters.\nParameters for this method:\nThe FastenerTypeIndex parameter has to match the standard and be valid for that hole type, or an error occurs.\nThe SSize parameter must be a valid size for fastener type, or an error occurs.\nThe Value1 through Value12 parameters are different for each type of hole. The possible values are as follows, organized by hole type. SOLIDWORKS ignores parameters set to -1.\nCounterbore Holes\nHead clearance\n- Added to either the input counterbore depth or the counterbore depth in the standard.\nParameters for all counterbore holes:\nCounterBore Diameter\nCounterBore Depth\nHeadClearance\nScrew Fit\nDrill Angle\nNear Csink Diameter\nNear Csink Angle\nBot Csink Diameter\nBot Csink Angle\nFar Csink Diameter\nFar Csink Angle\nOffset\nCountersink Holes\nHead clearance type\n- Value from\nswWzdHoleCounterSinkHeadClearanceTypes_e\n, which represents how to add the head clearance values to the hole.\nParameters for all countersink holes:\nNear Csink Diameter\nNear Csink Angle\nHead Clearance\nScrew Fit\nDrill Angle\nFar Csink Diameter\nFar Csink Angle\nOffset\nHead Clearance Type\nRegular Holes\nParameters for all holes:\nScrew Fit\nDrill Angle\nNear Csink Diameter\nNear Csink Angle\nFar Csink Diameter\nFar Csink Angle\nOffset\nPipe Tapped Holes\nTap Drill Depth\n- Depth can be set up as a ratio from the standard thread depth or the input thread depth. If the user does specify a tap drill depth, then the calculation from the thread depth is replaced with the specified depth.\nCosmetic Thread Type\n- Defaults to swCosmeticThreadNone from\nswWzdHoleCosmeticThreadTypes_e\n.\nNear countersink angle\n- Can be calculated from standard data as a default.\nParameters for all ptap holes:\nThread Depth\nNear Csink Diameter\nNear Csink Angle\nFar Csink Diameter\nFar Csink Angle\nDrill Angle\nCosmetic Thread Type\nOffset\nTap Holes\nTap Drill Depth\n- If the user specifies a tap drill depth, then SOLIDWORKS always uses this depth. Tap drill depths can be calculated:\nFor helicoil holes: Tap drill depth is calculated based on a constant * tap drill diameter + allowance for tap type (bottoming or plug).\nFor tapped holes: Tap drill depth is calculated from the thread length + advance + allowance for tap type (bottoming or plug).\nThread Depth\nIf the user specifies thread depth, then SOLIDWORKS always uses this depth. Tap drill depths can be calculated:\nFor helicoil holes: Thread depth is calculated based on a constant (determined by hole type i.e. Insert = 1.0 * diameter) + thread depth from the standard * thread major diameter.\nFor tapped holes: based on 2 * thread diameter.\nCosmetic Thread Type\n- Specified as defined in swWzdHoleCosmeticThreadTypes_e.\nHcoil Tap Type\n- Defaults to swTapTypePlug as defined in\nswWzdHoleHcoilTapTypes_e\n; used only for the helicoil standard holes.\nThread end condition\n- Defaults to swEndThreadTypeBLIND as defined in\nswWzdHoleThreadEndCondition_e\n.\nParameters for all ptap holes:\nTap drill diameter\nTap drill depth\nThread Depth\nNear Csink Diameter\nNear Csink Angle\nFar Csink Diameter\nFar Csink Angle\nDrill Angle\nCosmetic Thread Type\nThread End Condition\nHelicoil Tap Type\nOffset\nLegacy Holes\nFor legacy types of holes StandardIndex, FastenerTypeIndex, and SSize are not relevant and SOLIDWORKS ignores them.\nThe sequence of parameters 6 to 19 for different types of legacy holes is as follows:\nSimple\nDiameter\nDepth\nSketch ID\nTapered\nMinor Diameter\nDepth\nSketch ID\nMajor Diameter\nCounterbored\nDiameter\nDepth\nSketch ID\nC-Bore Diameter\nC-Bore Depth\nCountersunk\nDiameter\nDepth\nSketch ID\nC-Sink Angle\nC-Sink Diameter\nCounterdrilled\nDiameter\nDepth\nSketch ID\nC-Drill Diameter\nC-Drill Depth\nC-Drill Angle\nSimple Drilled\nDiameter\nDepth\nSketch ID\nDrill Angle\nTapered Drilled\nMinor Diameter\nDepth\nSketch ID\nMajor Diameter\nDrill Angle\nC-Bored Drilled\nDiameter\nDepth\nSketch ID\nC-Bore Diameter\nC-Bore Depth\nDrill Angle\nC-Sunk Drilled\nDiameter\nDepth\nSketch ID\nC-Sink Diameter\nC-Sink Angle\nDrill Angle\nC-Drilled Drilled\nDiameter\nDepth\nSketch ID\nC-Drill Diameter\nC-Drill Depth\nDrill Angle\nC-Drill Angle",
  "examples": [],
  "related": []
}