{
  "frontmatter": {
    "type": "interface",
    "interface": "IEnumModelViews",
    "inherits": null,
    "description": "Allows access to a\nmodel views\nenumeration.",
    "member_count": 4,
    "docset": "sldworksapi",
    "categories": [
      "core",
      "ui"
    ],
    "common_members": [
      "Clone",
      "Next",
      "Reset",
      "Skip"
    ]
  },
  "title": "IEnumModelViews",
  "description": "Allows access to a\nmodel views\nenumeration.",
  "common_members": [
    "Clone",
    "Next",
    "Reset",
    "Skip"
  ]
}