{
  "frontmatter": {
    "type": "method",
    "interface": "IModelDoc",
    "member": "ActivateSelectedFeature",
    "returns": "void",
    "parameters": [],
    "docset": "sldworksapi",
    "deprecated": true,
    "since_version": "unknown",
    "categories": [
      "features",
      "selections"
    ],
    "related": [],
    "keywords": [
      "activateselectedfeature",
      "imodeldoc",
      "model",
      "doc",
      "activate",
      "selected",
      "feature",
      "void"
    ]
  },
  "title": "IModelDoc.ActivateSelectedFeature",
  "description": "Obsolete. Superseded by IModelDoc2::ActivateSelectedFeature.",
  "signature": "void ActivateSelectedFeature()",
  "parameters": [],
  "returns": "",
  "remarks": "",
  "examples": [],
  "related": []
}