{
  "frontmatter": {
    "type": "method",
    "interface": "IModelDoc2",
    "member": "SetUserPreferenceDoubleValue",
    "returns": "System.Boolean",
    "parameters": [
      {
        "name": "UserPreferenceValue",
        "type": "System.Int32",
        "description": "User preference value as defined in swUserPreferenceDoubleValue_e"
      },
      {
        "name": "Value",
        "type": "System.Double",
        "description": "Numeric value to give to the user preference specified in UserPreferenceValue"
      }
    ],
    "docset": "sldworksapi",
    "deprecated": true,
    "since_version": "unknown",
    "categories": [
      "core",
      "documents",
      "ui"
    ],
    "related": [],
    "keywords": [
      "setuserpreferencedoublevalue",
      "imodeldoc2",
      "model",
      "doc2",
      "user",
      "preference",
      "double",
      "value",
      "int32",
      "boolean",
      "material",
      "density",
      "vba",
      "excel",
      "cell"
    ]
  },
  "title": "IModelDoc2.SetUserPreferenceDoubleValue",
  "description": "Obsolete. Superseded by IModelDocExtension::SetUserPreferenceDouble.",
  "signature": "System.Boolean SetUserPreferenceDoubleValue( \n   System.Int32\nUserPreferenceValue\n,\n   System.Double\nValue\n)",
  "parameters": [
    {
      "name": "UserPreferenceValue",
      "type": "System.Int32",
      "description": "User preference value as defined in swUserPreferenceDoubleValue_e"
    },
    {
      "name": "Value",
      "type": "System.Double",
      "description": "Numeric value to give to the user preference specified in UserPreferenceValue"
    }
  ],
  "returns": "True if the user preference is set successfully, false if not",
  "remarks": "This method is equivalent to interactively setting document properties in the SOLIDWORKS Design software. See\nSystem Options and Document Properties\nfor details.",
  "examples": [
    {
      "title": "Get and Set Material Density (VBA)",
      "href": "Get_and_Set_Material_Density_Example_VB.htm",
      "code_blocks": []
    },
    {
      "title": "Get Excel Cell Value for Density (VBA)",
      "href": "Get_Excel_Cell_Value_for_Density_Example_VB.htm",
      "code_blocks": []
    }
  ],
  "related": []
}