{
  "frontmatter": {
    "type": "method",
    "interface": "IPartDoc",
    "member": "SetCosmosWorksMaterial",
    "returns": "void",
    "parameters": [
      {
        "name": "ConfigName",
        "type": "System.String",
        "description": "Name of the configuration"
      },
      {
        "name": "Type",
        "type": "System.Int32",
        "description": "Type of material to assign as defined by swCosmosWorksMat"
      }
    ],
    "docset": "sldworksapi",
    "deprecated": false,
    "since_version": "unknown",
    "categories": [
      "core",
      "parts",
      "ui"
    ],
    "related": [
      "IComponent2.SetCosmosWorksMaterial"
    ],
    "keywords": [
      "analysis",
      "materials",
      "material",
      "parts",
      "see",
      "also",
      "ipartdoc",
      "setcosmosworksmaterial",
      "part",
      "doc",
      "cosmos",
      "works",
      "config",
      "name",
      "string",
      "type",
      "int32",
      "void"
    ]
  },
  "title": "IPartDoc.SetCosmosWorksMaterial",
  "description": "Assigns the material to use during analysis to this part.",
  "signature": "void SetCosmosWorksMaterial( \n   System.String\nConfigName\n,\n   System.Int32\nType\n)",
  "parameters": [
    {
      "name": "ConfigName",
      "type": "System.String",
      "description": "Name of the configuration"
    },
    {
      "name": "Type",
      "type": "System.Int32",
      "description": "Type of material to assign as defined by swCosmosWorksMat"
    }
  ],
  "returns": "True if the material is assigned, false if not",
  "remarks": "",
  "examples": [],
  "related": [
    "IComponent2.SetCosmosWorksMaterial"
  ]
}