{
  "frontmatter": {
    "type": "property",
    "interface": "ISurfaceParameterizationData",
    "member": "UMax",
    "returns": "System.Double",
    "parameters": [],
    "docset": "sldworksapi",
    "deprecated": false,
    "since_version": "unknown",
    "categories": [
      "documents"
    ],
    "related": [
      "ISurfaceParameterizationData.UMaxBoundType",
      "ISurfaceParameterizationData.UMin",
      "ISurfaceParameterizationData.UProperties"
    ],
    "keywords": [
      "umax",
      "isurfaceparameterizationdata",
      "surface",
      "parameterization",
      "data",
      "max",
      "double",
      "spline",
      "vb",
      "net",
      "vba"
    ],
    "readonly": true
  },
  "title": "ISurfaceParameterizationData.UMax",
  "description": "Gets the highest value in the U parameter range.",
  "signature": "System.Double UMax {get;}",
  "parameters": [],
  "returns": "Highest U parameter value",
  "remarks": "",
  "examples": [
    {
      "title": "Get B-Spline Surface Parameterization Data (C#)",
      "href": "Get_B-Spline_Surface_Parameterization_Data_Example_CSharp.htm",
      "code_blocks": []
    },
    {
      "title": "Get B-Spline Surface Parameterization Data (VB.NET)",
      "href": "Get_B-Spline_Surface_Parameterization_Data_Example_VBNET.htm",
      "code_blocks": []
    },
    {
      "title": "Get B-Spline Surface Parameterization Data (VBA)",
      "href": "Get_B-Spline_Surface_Parameterization_Data_Example_VB.htm",
      "code_blocks": []
    }
  ],
  "related": [
    "ISurfaceParameterizationData.UMaxBoundType",
    "ISurfaceParameterizationData.UMin",
    "ISurfaceParameterizationData.UProperties"
  ]
}