{
  "frontmatter": {
    "type": "method",
    "interface": "IMassProperty",
    "member": "IGetPrincipleMomentsOfInertia",
    "returns": "System.Double",
    "parameters": [],
    "docset": "sldworksapi",
    "deprecated": false,
    "since_version": "unknown",
    "categories": [
      "documents"
    ],
    "related": [
      "IMassProperty.GetMomentOfInertia",
      "IMassProperty.IGetMomentOfInertia",
      "IMassProperty.IGetPrincipleAxesOfInertia",
      "IMassProperty.PrincipleAxesOfInertia",
      "IMassProperty.PrincipleMomentsOfInertia"
    ],
    "keywords": [
      "igetprinciplemomentsofinertia",
      "imassproperty",
      "mass",
      "principle",
      "moments",
      "inertia",
      "double"
    ]
  },
  "title": "IMassProperty.IGetPrincipleMomentsOfInertia",
  "description": "Gets the principal moments of inertia for this model.",
  "signature": "System.Double IGetPrincipleMomentsOfInertia()",
  "parameters": [],
  "returns": "in-process, unmanaged C++: Pointer to an array of size 3 (see Remarks ) VBA, VB.NET, C#, and C++/CLI: Not supported See In-process Methods for details about this type of method.",
  "remarks": "This method returns\nmetric units unless explicitly specified otherwise.\nThe return value is a 0-based array of doubles:\n[\nPx, Py, Pz\n]",
  "examples": [],
  "related": [
    "IMassProperty.GetMomentOfInertia",
    "IMassProperty.IGetMomentOfInertia",
    "IMassProperty.IGetPrincipleAxesOfInertia",
    "IMassProperty.PrincipleAxesOfInertia",
    "IMassProperty.PrincipleMomentsOfInertia"
  ]
}