{
  "frontmatter": {
    "type": "method",
    "interface": "ISldWorks",
    "member": "SetUserPreferenceStringValue",
    "returns": "System.Boolean",
    "parameters": [
      {
        "name": "UserPreference",
        "type": "System.Int32",
        "description": "User preference as defined in swUserPreferenceStringValue_e"
      },
      {
        "name": "Value",
        "type": "System.String",
        "description": "Value of U serPreference"
      }
    ],
    "docset": "sldworksapi",
    "deprecated": false,
    "since_version": "unknown",
    "categories": [
      "core",
      "documents",
      "ui"
    ],
    "related": [
      "IModelDocExtension.GetUserPreferenceDouble",
      "IModelDocExtension.GetUserPreferenceDoubleValueRange",
      "IModelDocExtension.GetUserPreferenceInteger",
      "IModelDocExtension.GetUserPreferenceString",
      "IModelDocExtension.GetUserPreferenceTextFormat",
      "IModelDocExtension.GetUserPreferenceToggle",
      "IModelDocExtension.SetUserPreferenceDouble",
      "IModelDocExtension.SetUserPreferenceInteger",
      "IModelDocExtension.SetUserPreferenceString",
      "IModelDocExtension.SetUserPreferenceTextFormat",
      "IModelDocExtension.SetUserPreferenceToggle",
      "ISldWorks.GetUserPreferenceDoubleValue",
      "ISldWorks.GetUserPreferenceIntegerValue",
      "ISldWorks.GetUserPreferenceStringListValue",
      "ISldWorks.GetUserPreferenceStringValue",
      "ISldWorks.GetUserPreferenceToggle",
      "ISldWorks.SetUserPreferenceDoubleValue",
      "ISldWorks.SetUserPreferenceIntegerValue",
      "ISldWorks.SetUserPreferenceStringListValue",
      "ISldWorks.SetUserPreferenceToggle"
    ],
    "keywords": [
      "options",
      "user",
      "preferences",
      "setuserpreferencestringvalue",
      "isldworks",
      "sld",
      "works",
      "preference",
      "string",
      "value",
      "int32",
      "boolean",
      "change",
      "labels",
      "solidworks",
      "triad",
      "vba",
      "vb",
      "net"
    ]
  },
  "title": "ISldWorks.SetUserPreferenceStringValue",
  "description": "Sets system default user preference values.",
  "signature": "System.Boolean SetUserPreferenceStringValue( \n   System.Int32\nUserPreference\n,\n   System.String\nValue\n)",
  "parameters": [
    {
      "name": "UserPreference",
      "type": "System.Int32",
      "description": "User preference as defined in swUserPreferenceStringValue_e"
    },
    {
      "name": "Value",
      "type": "System.String",
      "description": "Value of U serPreference"
    }
  ],
  "returns": "True if UserPreference is set, false if not",
  "remarks": "This method is intended for user preferences of type string.\nThis method is equivalent to interactively setting system options in the SOLIDWORKS Design software.\nSee\nSystem Options and Document Properties\nfor details.",
  "examples": [
    {
      "title": "Change Labels of SOLIDWORKS Triad (VBA)",
      "href": "Change_Labels_of_SOLIDWORKS_Triad_Example_VB.htm",
      "code_blocks": []
    },
    {
      "title": "Get and Set User Preferences (VBA)",
      "href": "Get_and_Set_User_Preferences_Example_VB.htm",
      "code_blocks": []
    },
    {
      "title": "Get and Set User Preferences (VB.NET)",
      "href": "Get_and_Set_User_Preferences_Example_VBNET.htm",
      "code_blocks": []
    },
    {
      "title": "Get and Set User Preferences (C#)",
      "href": "Get_and_Set_User_Preferences_Example_CSharp.htm",
      "code_blocks": []
    }
  ],
  "related": [
    "IModelDocExtension.GetUserPreferenceDouble",
    "IModelDocExtension.GetUserPreferenceDoubleValueRange",
    "IModelDocExtension.GetUserPreferenceInteger",
    "IModelDocExtension.GetUserPreferenceString",
    "IModelDocExtension.GetUserPreferenceTextFormat",
    "IModelDocExtension.GetUserPreferenceToggle",
    "IModelDocExtension.SetUserPreferenceDouble",
    "IModelDocExtension.SetUserPreferenceInteger",
    "IModelDocExtension.SetUserPreferenceString",
    "IModelDocExtension.SetUserPreferenceTextFormat",
    "IModelDocExtension.SetUserPreferenceToggle",
    "ISldWorks.GetUserPreferenceDoubleValue",
    "ISldWorks.GetUserPreferenceIntegerValue",
    "ISldWorks.GetUserPreferenceStringListValue",
    "ISldWorks.GetUserPreferenceStringValue",
    "ISldWorks.GetUserPreferenceToggle",
    "ISldWorks.SetUserPreferenceDoubleValue",
    "ISldWorks.SetUserPreferenceIntegerValue",
    "ISldWorks.SetUserPreferenceStringListValue",
    "ISldWorks.SetUserPreferenceToggle"
  ]
}