{
  "frontmatter": {
    "type": "method",
    "interface": "IFeatureManager",
    "member": "InsertDeleteHoleForSurface",
    "returns": "Feature",
    "parameters": [],
    "docset": "sldworksapi",
    "deprecated": false,
    "since_version": "unknown",
    "categories": [
      "features"
    ],
    "related": [],
    "keywords": [
      "delete",
      "holes",
      "see",
      "also",
      "isimpleholefeaturedata2",
      "iwizardholefeaturedata2",
      "interfaces",
      "insertdeleteholeforsurface",
      "ifeaturemanager",
      "feature",
      "manager",
      "insert",
      "hole",
      "surface"
    ]
  },
  "title": "IFeatureManager.InsertDeleteHoleForSurface",
  "description": "Inserts a Delete Hole feature for one or more selected hole edges on a surface.",
  "signature": "Feature InsertDeleteHoleForSurface()",
  "parameters": [],
  "returns": "IFeature",
  "remarks": "Before calling this method, call\nIModelDocExtension::SelectByID2\nto select the hole edges to remove from the surface.",
  "examples": [],
  "related": []
}