{
  "frontmatter": {
    "type": "method",
    "interface": "ILinearPatternFeatureData",
    "member": "GetPatternFaceCount",
    "returns": "System.Int32",
    "parameters": [],
    "docset": "sldworksapi",
    "deprecated": false,
    "since_version": "unknown",
    "categories": [
      "features",
      "geometry"
    ],
    "related": [
      "ILinearPatternFeatureData.IGetPatternFaceArray",
      "ILinearPatternFeatureData.ISetPatternFaceArray",
      "ILinearPatternFeatureData.PatternFaceArray"
    ],
    "keywords": [
      "getpatternfacecount",
      "ilinearpatternfeaturedata",
      "linear",
      "pattern",
      "feature",
      "data",
      "face",
      "count",
      "int32"
    ]
  },
  "title": "ILinearPatternFeatureData.GetPatternFaceCount",
  "description": "Gets the number of seed faces in this linear pattern feature.",
  "signature": "System.Int32 GetPatternFaceCount()",
  "parameters": [],
  "returns": "Number of seed faces",
  "remarks": "",
  "examples": [],
  "related": [
    "ILinearPatternFeatureData.IGetPatternFaceArray",
    "ILinearPatternFeatureData.ISetPatternFaceArray",
    "ILinearPatternFeatureData.PatternFaceArray"
  ]
}