{
  "frontmatter": {
    "type": "property",
    "interface": "IExtrudeFeatureData2",
    "member": "AssemblyFeatureScope",
    "returns": "System.Boolean",
    "parameters": [],
    "docset": "sldworksapi",
    "deprecated": false,
    "since_version": "unknown",
    "categories": [
      "assemblies",
      "features"
    ],
    "related": [
      "IExtrudeFeatureData2.AutoSelect",
      "IExtrudeFeatureData2.AutoSelectComponents",
      "IExtrudeFeatureData2.PropagateFeatureToParts"
    ],
    "keywords": [
      "feature",
      "scope",
      "assemblies",
      "see",
      "also",
      "iassemblydoc",
      "assemblyfeaturescope",
      "iextrudefeaturedata2",
      "extrude",
      "data2",
      "assembly",
      "boolean"
    ],
    "readonly": null
  },
  "title": "IExtrudeFeatureData2.AssemblyFeatureScope",
  "description": "Gets or sets whether to use scope for this assembly extrude feature.",
  "signature": "System.Boolean AssemblyFeatureScope {get; set;}",
  "parameters": [],
  "returns": "True to use feature scope, false to not",
  "remarks": "",
  "examples": [],
  "related": [
    "IExtrudeFeatureData2.AutoSelect",
    "IExtrudeFeatureData2.AutoSelectComponents",
    "IExtrudeFeatureData2.PropagateFeatureToParts"
  ]
}