{
  "frontmatter": {
    "type": "property",
    "interface": "IOneBendFeatureData",
    "member": "BendAllowanceType",
    "returns": "System.Int32",
    "parameters": [],
    "docset": "sldworksapi",
    "deprecated": true,
    "since_version": "unknown",
    "categories": [
      "features"
    ],
    "related": [],
    "keywords": [
      "bendallowancetype",
      "ionebendfeaturedata",
      "one",
      "bend",
      "feature",
      "data",
      "allowance",
      "type",
      "int32"
    ],
    "readonly": null
  },
  "title": "IOneBendFeatureData.BendAllowanceType",
  "description": "Obsolete. Superseded by IOneBendFeatureData::GetCustomBendAllowance and IOneBendFeatureData::SetCustomBendAllowance.",
  "signature": "System.Int32 BendAllowanceType {get; set;}",
  "parameters": [],
  "returns": "",
  "remarks": "",
  "examples": [],
  "related": []
}