{
  "frontmatter": {
    "type": "enum",
    "name": "swAcisOutputGeometryPreference_e",
    "description": "ACIS output geometry types.",
    "member_count": 3,
    "docset": "swconst",
    "categories": [
      "constants"
    ],
    "used_by": []
  },
  "title": "swAcisOutputGeometryPreference_e",
  "description": "ACIS output geometry types.",
  "values": [
    {
      "member": "swAcisOutputAs3DCurves",
      "value": "1",
      "description": "= 3D curves without export sketch entities"
    },
    {
      "member": "swAcisOutputAs3DCurves_IncludeSketchEnts",
      "value": "2",
      "description": "= 3D curves with export sketch entities"
    },
    {
      "member": "swAcisOutputAsSolidAndSurface",
      "value": "0",
      "description": "= Solid/surface geometry"
    }
  ]
}