{
  "frontmatter": {
    "type": "enum",
    "name": "swHorizontalAutoSplitApply_e",
    "description": "Options for when to automatically split a table horizontally.",
    "member_count": 2,
    "docset": "swconst",
    "categories": [
      "constants"
    ],
    "used_by": []
  },
  "title": "swHorizontalAutoSplitApply_e",
  "description": "Options for when to automatically split a table horizontally.",
  "values": [
    {
      "member": "swHorizontalAutoSplitApply_Continuousely",
      "value": "1",
      "description": ""
    },
    {
      "member": "swHorizontalAutoSplitApply_ThisTimeOnly",
      "value": "0",
      "description": ""
    }
  ]
}