{
  "frontmatter": {
    "type": "enum",
    "name": "swPLYQuality_e",
    "description": "Polygon file format resolutions.",
    "member_count": 3,
    "docset": "swconst",
    "categories": [
      "constants"
    ],
    "used_by": []
  },
  "title": "swPLYQuality_e",
  "description": "Polygon file format resolutions.",
  "values": [
    {
      "member": "swPLYQuality_Coarse",
      "value": "1",
      "description": ""
    },
    {
      "member": "swPLYQuality_Custom",
      "value": "3",
      "description": ""
    },
    {
      "member": "swPLYQuality_Fine",
      "value": "2",
      "description": ""
    }
  ]
}