{
  "frontmatter": {
    "type": "method",
    "interface": "IPartDoc",
    "member": "GetTessTriangleCount",
    "returns": "System.Int32",
    "parameters": [],
    "docset": "sldworksapi",
    "deprecated": false,
    "since_version": "unknown",
    "categories": [
      "core",
      "parts",
      "ui"
    ],
    "related": [
      "IPartDoc.GetTessNorms",
      "IPartDoc.GetTessTriStripEdges",
      "IPartDoc.GetTessTriStripNorms",
      "IPartDoc.GetTessTriStripSize",
      "IPartDoc.GetTessTriStripTextures",
      "IPartDoc.GetTessTriStrips",
      "IPartDoc.GetTessTriangles",
      "IPartDoc.IGetTessNorms",
      "IPartDoc.IGetTessTriStripEdgeSize",
      "IPartDoc.IGetTessTriStripEdges",
      "IPartDoc.IGetTessTriStripNorms",
      "IPartDoc.IGetTessTriStrips",
      "IPartDoc.IGetTessTriangles",
      "ITessellation"
    ],
    "keywords": [
      "tessellation",
      "see",
      "also",
      "itessellation",
      "parts",
      "ipartdoc",
      "gettesstrianglecount",
      "part",
      "doc",
      "tess",
      "triangle",
      "count",
      "int32"
    ]
  },
  "title": "IPartDoc.GetTessTriangleCount",
  "description": "Gets the number of triangles that make up the shaded picture tessellation for this part.",
  "signature": "System.Int32 GetTessTriangleCount()",
  "parameters": [],
  "returns": "Number of triangles",
  "remarks": "",
  "examples": [],
  "related": [
    "IPartDoc.GetTessNorms",
    "IPartDoc.GetTessTriStripEdges",
    "IPartDoc.GetTessTriStripNorms",
    "IPartDoc.GetTessTriStripSize",
    "IPartDoc.GetTessTriStripTextures",
    "IPartDoc.GetTessTriStrips",
    "IPartDoc.GetTessTriangles",
    "IPartDoc.IGetTessNorms",
    "IPartDoc.IGetTessTriStripEdgeSize",
    "IPartDoc.IGetTessTriStripEdges",
    "IPartDoc.IGetTessTriStripNorms",
    "IPartDoc.IGetTessTriStrips",
    "IPartDoc.IGetTessTriangles",
    "ITessellation"
  ]
}